numproto/__init__.py
numproto/__version__.py
numproto/numproto.py
numproto/protobuf/__init__.py
numproto/protobuf/ndarray.proto
numproto/protobuf/ndarray_pb2.py
numproto/protobuf/ndarray_pb2.pyi
numproto/protobuf/ndarray_pb2_grpc.py
numproto-0.3.0.dist-info/LICENSE
numproto-0.3.0.dist-info/METADATA
numproto-0.3.0.dist-info/WHEEL
numproto-0.3.0.dist-info/top_level.txt
numproto-0.3.0.dist-info/RECORD
