Metadata-Version: 2.1
Name: numproto
Version: 0.3.0
Summary: NumProto provides NumPy ndarray to protobuf conversion.
Home-page: https://github.com/xainag/numproto
Author: NumProto Contributors
Author-email: services@xain.io
License: Apache License Version 2.0
Platform: UNKNOWN
Classifier: Development Status :: 3 - Alpha
Classifier: Intended Audience :: Developers
Classifier: Topic :: Software Development
Classifier: Topic :: Scientific/Engineering
Classifier: License :: OSI Approved :: Apache Software License
Classifier: Programming Language :: Python :: 3 :: Only
Classifier: Programming Language :: Python :: 3.6
Classifier: Programming Language :: Python :: 3.7
Classifier: Programming Language :: Python :: 3.8
Classifier: Operating System :: MacOS :: MacOS X
Classifier: Operating System :: POSIX :: Linux
Requires-Python: >=3.6
Requires-Dist: numpy (~=1.15)
Requires-Dist: protobuf (~=3.9)
Requires-Dist: grpcio (~=1.23)
Provides-Extra: dev
Requires-Dist: grpcio-tools (~=1.23) ; extra == 'dev'
Requires-Dist: isort (==4.3.20) ; extra == 'dev'
Requires-Dist: black (==19.3b0) ; extra == 'dev'
Requires-Dist: mypy (==0.720) ; extra == 'dev'
Requires-Dist: mypy-protobuf (==1.15) ; extra == 'dev'
Requires-Dist: pylint (==2.3.1) ; extra == 'dev'
Requires-Dist: pytest (==5.1.2) ; extra == 'dev'
Provides-Extra: test
Requires-Dist: pytest (==5.1.2) ; extra == 'test'
